{
  "codeSystems" : [
    {
      "url" : "http://hl7.org/fhir/ValueSet/administrative-gender",
      "version" : "4.0.1",
      "status" : "active",
      "name" : "AdministrativeGender",
      "title" : "AdministrativeGender",
      "description" : "The gender of a person used for administrative purposes.",
      "systems" : ["http://hl7.org/fhir/administrative-gender"],
      "oids" : ["2.16.840.1.113883.4.642.3.1"],
      "sources" : ["2.16.840.1.113883.4.642.3.1"],
      "uses" : {
      },
      "StructureDefinition-PatientSNS.html" : "Paciente"
    },
    {
      "url" : "http://sns.gob.es/fhir/tsi/ValueSet/aseguradorasVS",
      "version" : "1.0.0",
      "status" : "draft",
      "name" : "AseguradorasVS",
      "title" : "ValueSet Aseguradoras",
      "description" : "ValueSet Aseguradoras",
      "systems" : ["http://sns.gob.es/fhir/tsi/CodeSystem/aseguradorasCS"],
      "uses" : {
      },
      "StructureDefinition-patient-coverage-insurance.html" : "Entidades Aseguradoras coberturas paciente"
    },
    {
      "url" : "http://sns.gob.es/fhir/tsi/ValueSet/colaboradorasVS",
      "version" : "1.0.0",
      "status" : "draft",
      "name" : "ColaboradorasVS",
      "title" : "ValueSet Colaboradoras",
      "description" : "ValueSet Colaboradoras",
      "systems" : ["http://sns.gob.es/fhir/tsi/CodeSystem/colaboradorasCS"],
      "uses" : {
      },
      "StructureDefinition-patient-coverage-entities.html" : "Entidades Colaboradoras coberturas paciente"
    },
    {
      "url" : "http://sns.gob.es/fhir/tsi/ValueSet/comunidadesAutonomasVS",
      "version" : "1.0.0",
      "status" : "draft",
      "name" : "ComunidadesAutonomasVS",
      "title" : "ValueSet Comunidades Autónomas",
      "description" : "ValueSet Comunidades Autónomas",
      "systems" : [
        "http://sns.gob.es/fhir/tsi/CodeSystem/comunidadesAutonomasCS"
      ],
      "uses" : {
      },
      "StructureDefinition-patient-inscription-community.html" : "CA Inscripción coberturas paciente",
      "StructureDefinition-patient-temporalidad-ca.html" : "CA Temporalidad",
      "StructureDefinition-patient-birth-community.html" : "CA Nacimiento paciente",
      "StructureDefinition-patient-adscription-community.html" : "CA Adscripción paciente"
    },
    {
      "url" : "http://sns.gob.es/fhir/tsi/ValueSet/estadoIndefVS",
      "version" : "1.0.0",
      "status" : "draft",
      "name" : "EstadoIndefVS",
      "title" : "ValueSet comprobación Fecha Defunción",
      "description" : "ValueSet comprobación Fecha Defunción",
      "systems" : ["http://sns.gob.es/fhir/tsi/CodeSystem/estadoIndefCS"],
      "uses" : {
      },
      "StructureDefinition-estado-comprobacion-indef.html" : "Estado comprobación fecha defunción"
    },
    {
      "url" : "http://sns.gob.es/fhir/tsi/ValueSet/estadosVS",
      "version" : "1.0.0",
      "status" : "draft",
      "name" : "EstadosVS",
      "title" : "ValueSet Estado Paciente",
      "description" : "ValueSet Estado Paciente",
      "systems" : ["http://sns.gob.es/fhir/tsi/CodeSystem/estadosCS"],
      "uses" : {
      },
      "StructureDefinition-patient-passive-cause.html" : "Motivo Causa Pasivo"
    },
    {
      "url" : "http://sns.gob.es/fhir/tsi/ValueSet/gestorasVS",
      "version" : "1.0.0",
      "status" : "draft",
      "name" : "GestorasVS",
      "title" : "ValueSet Gestoras",
      "description" : "ValueSet Gestoras",
      "systems" : ["http://sns.gob.es/fhir/tsi/CodeSystem/gestorasCS"],
      "uses" : {
      },
      "StructureDefinition-patient-coverage-mgt.html" : "Entidades Gestoras coberturas paciente"
    },
    {
      "url" : "http://sns.gob.es/fhir/tsi/ValueSet/indicadorFarmaciaVS",
      "version" : "1.0.0",
      "status" : "draft",
      "name" : "IndicadorFarmaciaVS",
      "title" : "Indicador Farmacia ValueSet",
      "description" : "Indicador Farmacia ValueSet",
      "systems" : ["http://sns.gob.es/fhir/tsi/CodeSystem/indicadorFarmaciaCS"],
      "uses" : {
      },
      "StructureDefinition-patient-pharmacy-indicator.html" : "Indicador Farmacia paciente"
    },
    {
      "url" : "http://sns.gob.es/fhir/tsi/ValueSet/municipiosVS",
      "version" : "1.0.0",
      "status" : "draft",
      "name" : "MunicipiosVS",
      "title" : "ValueSet Municipios",
      "description" : "ValueSet Municipios",
      "systems" : ["http://sns.gob.es/fhir/tsi/CodeSystem/municipiosCS"],
      "uses" : {
      },
      "StructureDefinition-patient-address-municipio.html" : "Municipio"
    },
    {
      "url" : "http://sns.gob.es/fhir/tsi/ValueSet/nacionalidadesVS",
      "version" : "1.0.0",
      "status" : "draft",
      "name" : "NacionalidadesVS",
      "title" : "ValueSet Nacionalidades",
      "description" : "ValueSet Nacionalidades",
      "systems" : ["http://sns.gob.es/fhir/tsi/CodeSystem/nacionalidadesCS"]
    },
    {
      "url" : "http://sns.gob.es/fhir/tsi/ValueSet/paisesVS",
      "version" : "1.0.0",
      "status" : "draft",
      "name" : "PaisesVS",
      "title" : "ValueSet Paises",
      "description" : "ValueSet Paises",
      "systems" : ["http://sns.gob.es/fhir/tsi/CodeSystem/paisesCS"],
      "uses" : {
      },
      "StructureDefinition-patient-birth-country.html" : "Pais Nacimiento paciente"
    },
    {
      "url" : "http://sns.gob.es/fhir/tsi/ValueSet/proveedoresVS",
      "version" : "1.0.0",
      "status" : "draft",
      "name" : "ProveedoresVS",
      "title" : "ValueSet Proveedores",
      "description" : "ValueSet Proveedores",
      "systems" : ["http://sns.gob.es/fhir/tsi/CodeSystem/proveedoresCS"],
      "uses" : {
      },
      "StructureDefinition-patient-coverage-providers.html" : "Proveedores coberturas paciente"
    },
    {
      "url" : "http://sns.gob.es/fhir/tsi/ValueSet/provinciasVS",
      "version" : "1.0.0",
      "status" : "draft",
      "name" : "ProvinciasVS",
      "title" : "ValueSet Provincias",
      "description" : "ValueSet Provincias",
      "systems" : ["http://sns.gob.es/fhir/tsi/CodeSystem/provinciasCS"],
      "uses" : {
      },
      "StructureDefinition-patient-address-provincia.html" : "Provincia"
    },
    {
      "url" : "http://sns.gob.es/fhir/tsi/ValueSet/situacionesVS",
      "version" : "1.0.0",
      "status" : "draft",
      "name" : "SituacionesVS",
      "title" : "ValueSet Situaciones",
      "description" : "ValueSet Situaciones",
      "systems" : ["http://sns.gob.es/fhir/tsi/CodeSystem/situacionesCS"],
      "uses" : {
      },
      "StructureDefinition-patient-coverage-situation.html" : "Situación coberturas paciente"
    },
    {
      "url" : "http://sns.gob.es/fhir/tsi/ValueSet/subIndicadorFarmaciaVS",
      "version" : "1.0.0",
      "status" : "draft",
      "name" : "SubIndicadorFarmaciaVS",
      "title" : "ValueSet Subindicador Farmacia",
      "description" : "ValueSet Subindicador Farmacia",
      "systems" : [
        "http://sns.gob.es/fhir/tsi/CodeSystem/subIndicadorFarmaciaCS"
      ],
      "uses" : {
      },
      "StructureDefinition-patient-pharmacy-subindicator.html" : "SubIndicador Farmacia paciente"
    },
    {
      "url" : "http://sns.gob.es/fhir/tsi/ValueSet/tipoViaVS",
      "version" : "1.0.0",
      "status" : "draft",
      "name" : "TipoViaVS",
      "title" : "ValueSet Tipo de Via",
      "description" : "ValueSet Tipo de Via",
      "systems" : ["http://sns.gob.es/fhir/tsi/CodeSystem/tipoViaCS"],
      "uses" : {
      },
      "StructureDefinition-iso21090-ADXP-streetNameType.html" : "Tipo Via"
    },
    {
      "url" : "http://sns.gob.es/fhir/tsi/ValueSet/titulosVS",
      "version" : "1.0.0",
      "status" : "draft",
      "name" : "TitulosVS",
      "title" : "ValueSet Titulos",
      "description" : "ValueSet Titulos",
      "systems" : ["http://sns.gob.es/fhir/tsi/CodeSystem/titulosCS"],
      "uses" : {
      },
      "StructureDefinition-patient-coverage-title.html" : "Titulo coberturas paciente"
    }
  ]
}
